{
  "meta": {
    "updated_at": "2026-03-27",
    "source": "OpenVan.camp fuel API",
    "source_url": "https://openvan.camp/api/fuel/prices",
    "license": "CC BY 4.0 (attribute OpenVan.camp when displaying)",
    "countries_count": 83
  },
  "countries": [
    {
      "country_code": "AL",
      "country": "Albania",
      "currency": "EUR",
      "gasoline": 1.881,
      "diesel": 1.934,
      "updated_at": "2026-03-15",
      "source_note": "Fuelo.net"
    },
    {
      "country_code": "DZ",
      "country": "Algeria",
      "currency": "DZD",
      "gasoline": 47,
      "diesel": 31,
      "updated_at": "2026-03-18",
      "source_note": "Ministère de l'Energie et des Mines (Algeria) — official tariff"
    },
    {
      "country_code": "AD",
      "country": "Andorra",
      "currency": "EUR",
      "gasoline": 1.05,
      "diesel": 0.95,
      "updated_at": "2026-03-15",
      "source_note": "carburant.ad (Andorra) — fallback"
    },
    {
      "country_code": "AR",
      "country": "Argentina",
      "currency": "ARS",
      "gasoline": 1258.8245,
      "diesel": 1384.4458,
      "updated_at": "2026-03-18",
      "source_note": "GobEnergy Argentina"
    },
    {
      "country_code": "AM",
      "country": "Armenia",
      "currency": "AMD",
      "gasoline": 460,
      "diesel": 470,
      "updated_at": "2026-03-18",
      "source_note": "autotraveler.ru (исторические цены на топливо, Армения)"
    },
    {
      "country_code": "AU",
      "country": "Australia",
      "currency": "EUR",
      "gasoline": 1.3854,
      "diesel": 1.6054,
      "updated_at": "2026-03-15",
      "source_note": "FuelWatch WA"
    },
    {
      "country_code": "AT",
      "country": "Austria",
      "currency": "EUR",
      "gasoline": 1.708,
      "diesel": 1.898,
      "updated_at": "2026-03-18",
      "source_note": "EU Weekly Oil Bulletin"
    },
    {
      "country_code": "AZ",
      "country": "Azerbaijan",
      "currency": "EUR",
      "gasoline": 0.6261,
      "diesel": 0.5989,
      "updated_at": "2026-03-15",
      "source_note": "OilPricez.com"
    },
    {
      "country_code": "BY",
      "country": "Belarus",
      "currency": "BYN",
      "gasoline": 2.6,
      "diesel": 2.6,
      "updated_at": "2026-03-18",
      "source_note": "GlobalPetrolPrices.com"
    },
    {
      "country_code": "BE",
      "country": "Belgium",
      "currency": "EUR",
      "gasoline": 1.628,
      "diesel": 1.846,
      "updated_at": "2026-03-18",
      "source_note": "EU Weekly Oil Bulletin"
    },
    {
      "country_code": "BO",
      "country": "Bolivia",
      "currency": "BOB",
      "gasoline": 6.96,
      "diesel": 9.8,
      "updated_at": "2026-03-18",
      "source_note": "GlobalPetrolPrices.com"
    },
    {
      "country_code": "BA",
      "country": "Bosnia & Herzegovina",
      "currency": "EUR",
      "gasoline": 1.1866,
      "diesel": 1.431,
      "updated_at": "2026-03-15",
      "source_note": "Fuelo.net"
    },
    {
      "country_code": "BR",
      "country": "Brazil",
      "currency": "BRL",
      "gasoline": 6.349,
      "diesel": 6.3077,
      "updated_at": "2026-03-18",
      "source_note": "ANP Brazil"
    },
    {
      "country_code": "BG",
      "country": "Bulgaria",
      "currency": "EUR",
      "gasoline": 1.266,
      "diesel": 1.306,
      "updated_at": "2026-03-18",
      "source_note": "EU Weekly Oil Bulletin"
    },
    {
      "country_code": "CA",
      "country": "Canada",
      "currency": "CAD",
      "gasoline": 1.36,
      "diesel": 1.55,
      "updated_at": "2026-03-18",
      "source_note": "GlobalPetrolPrices.com"
    },
    {
      "country_code": "CL",
      "country": "Chile",
      "currency": "USD",
      "gasoline": 1.34,
      "diesel": 1.03,
      "updated_at": "2026-03-18",
      "source_note": "GlobalPetrolPrices.com (fallback)"
    },
    {
      "country_code": "CN",
      "country": "China",
      "currency": "CNY",
      "gasoline": 8.21,
      "diesel": 7.3,
      "updated_at": "2026-03-18",
      "source_note": "GlobalPetrolPrices.com"
    },
    {
      "country_code": "CO",
      "country": "Colombia",
      "currency": "USD",
      "gasoline": 1.08,
      "diesel": 0.79,
      "updated_at": "2026-03-18",
      "source_note": "GlobalPetrolPrices.com"
    },
    {
      "country_code": "HR",
      "country": "Croatia",
      "currency": "EUR",
      "gasoline": 1.499,
      "diesel": 1.544,
      "updated_at": "2026-03-18",
      "source_note": "EU Weekly Oil Bulletin"
    },
    {
      "country_code": "CY",
      "country": "Cyprus",
      "currency": "EUR",
      "gasoline": 1.346,
      "diesel": 1.461,
      "updated_at": "2026-03-18",
      "source_note": "EU Weekly Oil Bulletin"
    },
    {
      "country_code": "CZ",
      "country": "Czechia",
      "currency": "EUR",
      "gasoline": 1.488,
      "diesel": 1.603,
      "updated_at": "2026-03-18",
      "source_note": "EU Weekly Oil Bulletin"
    },
    {
      "country_code": "DK",
      "country": "Denmark",
      "currency": "EUR",
      "gasoline": 2.058,
      "diesel": 2.114,
      "updated_at": "2026-03-18",
      "source_note": "EU Weekly Oil Bulletin"
    },
    {
      "country_code": "EC",
      "country": "Ecuador",
      "currency": "USD",
      "gasoline": 0.73,
      "diesel": 0.71,
      "updated_at": "2026-03-18",
      "source_note": "GlobalPetrolPrices.com"
    },
    {
      "country_code": "EG",
      "country": "Egypt",
      "currency": "EGP",
      "gasoline": 20.5,
      "diesel": 20.5,
      "updated_at": "2026-03-18",
      "source_note": "Кабинет министров Египта — official tariff"
    },
    {
      "country_code": "EE",
      "country": "Estonia",
      "currency": "EUR",
      "gasoline": 1.587,
      "diesel": 1.688,
      "updated_at": "2026-03-18",
      "source_note": "EU Weekly Oil Bulletin"
    },
    {
      "country_code": "FJ",
      "country": "Fiji",
      "currency": "FJD",
      "gasoline": 2.94,
      "diesel": 2.14,
      "updated_at": "2026-03-18",
      "source_note": "FCCC (Fijian Competition and Consumer Commission) — fallback"
    },
    {
      "country_code": "FI",
      "country": "Finland",
      "currency": "EUR",
      "gasoline": 1.926,
      "diesel": 2.042,
      "updated_at": "2026-03-18",
      "source_note": "EU Weekly Oil Bulletin"
    },
    {
      "country_code": "FR",
      "country": "France",
      "currency": "EUR",
      "gasoline": 1.842,
      "diesel": 1.952,
      "updated_at": "2026-03-18",
      "source_note": "EU Weekly Oil Bulletin"
    },
    {
      "country_code": "GE",
      "country": "Georgia",
      "currency": "GEL",
      "gasoline": 3.12,
      "diesel": 3.13,
      "updated_at": "2026-03-18",
      "source_note": "GlobalPetrolPrices.com"
    },
    {
      "country_code": "DE",
      "country": "Germany",
      "currency": "EUR",
      "gasoline": 2.075,
      "diesel": 2.163,
      "updated_at": "2026-03-18",
      "source_note": "EU Weekly Oil Bulletin"
    },
    {
      "country_code": "GR",
      "country": "Greece",
      "currency": "EUR",
      "gasoline": 1.852,
      "diesel": 1.814,
      "updated_at": "2026-03-18",
      "source_note": "EU Weekly Oil Bulletin"
    },
    {
      "country_code": "HK",
      "country": "Hong Kong SAR China",
      "currency": "EUR",
      "gasoline": 3.7135,
      "diesel": 3.7135,
      "updated_at": "2026-03-15",
      "source_note": "Consumer Council Hong Kong"
    },
    {
      "country_code": "HU",
      "country": "Hungary",
      "currency": "EUR",
      "gasoline": 1.498,
      "diesel": 1.592,
      "updated_at": "2026-03-18",
      "source_note": "EU Weekly Oil Bulletin"
    },
    {
      "country_code": "IS",
      "country": "Iceland",
      "currency": "EUR",
      "gasoline": 1.4304,
      "diesel": 1.5565,
      "updated_at": "2026-03-15",
      "source_note": "Gasvaktin Iceland"
    },
    {
      "country_code": "IN",
      "country": "India",
      "currency": "EUR",
      "gasoline": 1.0524,
      "diesel": 0.9736,
      "updated_at": "2026-03-15",
      "source_note": "IOCL India — fallback"
    },
    {
      "country_code": "IE",
      "country": "Ireland",
      "currency": "EUR",
      "gasoline": 1.747,
      "diesel": 1.747,
      "updated_at": "2026-03-18",
      "source_note": "EU Weekly Oil Bulletin"
    },
    {
      "country_code": "IL",
      "country": "Israel",
      "currency": "EUR",
      "gasoline": 1.8,
      "diesel": 1.575,
      "updated_at": "2026-03-15",
      "source_note": "Ministry of Energy Israel — fallback"
    },
    {
      "country_code": "IT",
      "country": "Italy",
      "currency": "EUR",
      "gasoline": 1.745,
      "diesel": 1.869,
      "updated_at": "2026-03-18",
      "source_note": "EU Weekly Oil Bulletin"
    },
    {
      "country_code": "JP",
      "country": "Japan",
      "currency": "EUR",
      "gasoline": 1.005,
      "diesel": 0.9306,
      "updated_at": "2026-03-15",
      "source_note": "ANRE/METI Japan — Weekly Retail Survey (enecho.meti.go.jp)"
    },
    {
      "country_code": "JO",
      "country": "Jordan",
      "currency": "EUR",
      "gasoline": 1.1619,
      "diesel": 1.0053,
      "updated_at": "2026-03-15",
      "source_note": "MEMR Jordan — fallback"
    },
    {
      "country_code": "KZ",
      "country": "Kazakhstan",
      "currency": "KZT",
      "gasoline": 235,
      "diesel": 330,
      "updated_at": "2026-03-18",
      "source_note": "Бюро национальной статистики РК (stat.gov.kz)"
    },
    {
      "country_code": "KG",
      "country": "Kyrgyzstan",
      "currency": "EUR",
      "gasoline": 0.7454,
      "diesel": 0.8643,
      "updated_at": "2026-03-15",
      "source_note": "NatStatCom Kyrgyzstan — fallback"
    },
    {
      "country_code": "LV",
      "country": "Latvia",
      "currency": "EUR",
      "gasoline": 1.633,
      "diesel": 1.792,
      "updated_at": "2026-03-18",
      "source_note": "EU Weekly Oil Bulletin"
    },
    {
      "country_code": "LB",
      "country": "Lebanon",
      "currency": "EUR",
      "gasoline": 0.703,
      "diesel": 0.6399,
      "updated_at": "2026-03-15",
      "source_note": "Ministry of Energy Lebanon (energyandwater.gov.lb)"
    },
    {
      "country_code": "LI",
      "country": "Liechtenstein",
      "currency": "EUR",
      "gasoline": null,
      "diesel": 2.069,
      "updated_at": "2026-03-15",
      "source_note": "Tankstellenpreise.de (Liechtenstein)"
    },
    {
      "country_code": "LT",
      "country": "Lithuania",
      "currency": "EUR",
      "gasoline": 1.576,
      "diesel": 1.901,
      "updated_at": "2026-03-18",
      "source_note": "EU Weekly Oil Bulletin"
    },
    {
      "country_code": "LU",
      "country": "Luxembourg",
      "currency": "EUR",
      "gasoline": 1.567,
      "diesel": 1.772,
      "updated_at": "2026-03-18",
      "source_note": "EU Weekly Oil Bulletin"
    },
    {
      "country_code": "MT",
      "country": "Malta",
      "currency": "EUR",
      "gasoline": 1.34,
      "diesel": 1.21,
      "updated_at": "2026-03-18",
      "source_note": "EU Weekly Oil Bulletin"
    },
    {
      "country_code": "MX",
      "country": "Mexico",
      "currency": "MXN",
      "gasoline": 23.5,
      "diesel": 27.29,
      "updated_at": "2026-03-18",
      "source_note": "CRE (Comisión Reguladora de Energía, México) — fallback"
    },
    {
      "country_code": "MD",
      "country": "Moldova",
      "currency": "EUR",
      "gasoline": 1.2987,
      "diesel": 1.263,
      "updated_at": "2026-03-15",
      "source_note": "Fuelo.net"
    },
    {
      "country_code": "MC",
      "country": "Monaco",
      "currency": "EUR",
      "gasoline": 1.661,
      "diesel": 1.8,
      "updated_at": "2026-03-15",
      "source_note": "Monaco Fuel Prices — fallback"
    },
    {
      "country_code": "ME",
      "country": "Montenegro",
      "currency": "EUR",
      "gasoline": 1.7,
      "diesel": 1.73,
      "updated_at": "2026-03-18",
      "source_note": "GlobalPetrolPrices.com"
    },
    {
      "country_code": "MA",
      "country": "Morocco",
      "currency": "EUR",
      "gasoline": 1.1463,
      "diesel": 0.9963,
      "updated_at": "2026-03-15",
      "source_note": "OilPricez.com"
    },
    {
      "country_code": "NL",
      "country": "Netherlands",
      "currency": "EUR",
      "gasoline": 2.171,
      "diesel": 2.255,
      "updated_at": "2026-03-18",
      "source_note": "EU Weekly Oil Bulletin"
    },
    {
      "country_code": "NZ",
      "country": "New Zealand",
      "currency": "EUR",
      "gasoline": 1.4349,
      "diesel": 1.08,
      "updated_at": "2026-03-15",
      "source_note": "MBIE New Zealand"
    },
    {
      "country_code": "MK",
      "country": "North Macedonia",
      "currency": "EUR",
      "gasoline": 1.2882,
      "diesel": 1.3854,
      "updated_at": "2026-03-15",
      "source_note": "Fuelo.net"
    },
    {
      "country_code": "NO",
      "country": "Norway",
      "currency": "EUR",
      "gasoline": 1.6869,
      "diesel": 1.6638,
      "updated_at": "2026-03-15",
      "source_note": "Statistics Norway (SSB)"
    },
    {
      "country_code": "PG",
      "country": "Papua New Guinea",
      "currency": "PGK",
      "gasoline": 3.8,
      "diesel": 3.6,
      "updated_at": "2026-03-18",
      "source_note": "ICCC (Papua New Guinea) — fallback"
    },
    {
      "country_code": "PY",
      "country": "Paraguay",
      "currency": "USD",
      "gasoline": 1.05,
      "diesel": 1.24,
      "updated_at": "2026-03-18",
      "source_note": "GlobalPetrolPrices.com"
    },
    {
      "country_code": "PE",
      "country": "Peru",
      "currency": "PEN",
      "gasoline": 5.26,
      "diesel": 5.29,
      "updated_at": "2026-03-18",
      "source_note": "GlobalPetrolPrices.com"
    },
    {
      "country_code": "PH",
      "country": "Philippines",
      "currency": "PHP",
      "gasoline": 61.25,
      "diesel": 58.1,
      "updated_at": "2026-03-27",
      "source_note": null
    },
    {
      "country_code": "PL",
      "country": "Poland",
      "currency": "EUR",
      "gasoline": 1.5,
      "diesel": 1.73,
      "updated_at": "2026-03-18",
      "source_note": "EU Weekly Oil Bulletin"
    },
    {
      "country_code": "PT",
      "country": "Portugal",
      "currency": "EUR",
      "gasoline": 1.776,
      "diesel": 1.817,
      "updated_at": "2026-03-18",
      "source_note": "EU Weekly Oil Bulletin"
    },
    {
      "country_code": "RO",
      "country": "Romania",
      "currency": "EUR",
      "gasoline": 1.625,
      "diesel": 1.704,
      "updated_at": "2026-03-18",
      "source_note": "EU Weekly Oil Bulletin"
    },
    {
      "country_code": "RU",
      "country": "Russia",
      "currency": "RUB",
      "gasoline": 62.62,
      "diesel": 77.34,
      "updated_at": "2026-03-18",
      "source_note": "Росстат (Федеральная служба государственной статистики России)"
    },
    {
      "country_code": "RS",
      "country": "Serbia",
      "currency": "EUR",
      "gasoline": 1.5636,
      "diesel": 1.7297,
      "updated_at": "2026-03-15",
      "source_note": "Fuelo.net"
    },
    {
      "country_code": "SK",
      "country": "Slovakia",
      "currency": "EUR",
      "gasoline": 1.487,
      "diesel": 1.483,
      "updated_at": "2026-03-18",
      "source_note": "EU Weekly Oil Bulletin"
    },
    {
      "country_code": "SI",
      "country": "Slovenia",
      "currency": "EUR",
      "gasoline": 1.434,
      "diesel": 1.462,
      "updated_at": "2026-03-18",
      "source_note": "EU Weekly Oil Bulletin"
    },
    {
      "country_code": "KR",
      "country": "South Korea",
      "currency": "EUR",
      "gasoline": 1.1456,
      "diesel": 1.0298,
      "updated_at": "2026-03-15",
      "source_note": "Opinet Korea — fallback (март 2026)"
    },
    {
      "country_code": "ES",
      "country": "Spain",
      "currency": "EUR",
      "gasoline": 1.6,
      "diesel": 1.645,
      "updated_at": "2026-03-18",
      "source_note": "EU Weekly Oil Bulletin"
    },
    {
      "country_code": "SE",
      "country": "Sweden",
      "currency": "EUR",
      "gasoline": 1.511,
      "diesel": 1.782,
      "updated_at": "2026-03-18",
      "source_note": "EU Weekly Oil Bulletin"
    },
    {
      "country_code": "CH",
      "country": "Switzerland",
      "currency": "EUR",
      "gasoline": 1.8669,
      "diesel": 2.0618,
      "updated_at": "2026-03-15",
      "source_note": "Fuelo.net"
    },
    {
      "country_code": "TJ",
      "country": "Tajikistan",
      "currency": "EUR",
      "gasoline": 0.7217,
      "diesel": 0.8066,
      "updated_at": "2026-03-15",
      "source_note": "Tajikistan Fuel Prices — fallback"
    },
    {
      "country_code": "TH",
      "country": "Thailand",
      "currency": "EUR",
      "gasoline": 0.9785,
      "diesel": 0.8039,
      "updated_at": "2026-03-15",
      "source_note": "EPPO Thailand — fallback"
    },
    {
      "country_code": "TN",
      "country": "Tunisia",
      "currency": "EUR",
      "gasoline": 0.7567,
      "diesel": 0.661,
      "updated_at": "2026-03-15",
      "source_note": "OilPricez.com"
    },
    {
      "country_code": "TR",
      "country": "Türkiye",
      "currency": "TRY",
      "gasoline": 61.9,
      "diesel": 65.9,
      "updated_at": "2026-03-18",
      "source_note": "GlobalPetrolPrices.com"
    },
    {
      "country_code": "TM",
      "country": "Turkmenistan",
      "currency": "TMT",
      "gasoline": 1.5,
      "diesel": 1,
      "updated_at": "2026-03-18",
      "source_note": "Türkmennebit (государственные цены, Туркменистан)"
    },
    {
      "country_code": "UA",
      "country": "Ukraine",
      "currency": "EUR",
      "gasoline": 1.4486,
      "diesel": 1.5965,
      "updated_at": "2026-03-15",
      "source_note": "Fuelo.net"
    },
    {
      "country_code": "AE",
      "country": "United Arab Emirates",
      "currency": "EUR",
      "gasoline": 0.6573,
      "diesel": 0.675,
      "updated_at": "2026-03-15",
      "source_note": "UAE Fuel Price Committee"
    },
    {
      "country_code": "GB",
      "country": "United Kingdom",
      "currency": "EUR",
      "gasoline": 2.2319,
      "diesel": 2.4236,
      "updated_at": "2026-03-15",
      "source_note": "Fuelo.net"
    },
    {
      "country_code": "US",
      "country": "United States",
      "currency": "USD",
      "gasoline": 1.08,
      "diesel": 1.34,
      "updated_at": "2026-03-18",
      "source_note": "GlobalPetrolPrices.com"
    },
    {
      "country_code": "UY",
      "country": "Uruguay",
      "currency": "UYU",
      "gasoline": 76.88,
      "diesel": 47.32,
      "updated_at": "2026-03-18",
      "source_note": "GlobalPetrolPrices.com"
    },
    {
      "country_code": "UZ",
      "country": "Uzbekistan",
      "currency": "EUR",
      "gasoline": 0.8089,
      "diesel": 0.9028,
      "updated_at": "2026-03-15",
      "source_note": "Autostrada.uz (Uzbekistan)"
    }
  ]
}
